django_notification_sender-1.0.0.dist-info/licenses/LICENSE
notifications/__init__.py
notifications/admin.py
notifications/apps.py
notifications/blocks.py
notifications/models.py
notifications/urls.py
notifications/utils.py
notifications/views.py
notifications/management/__init__.py
notifications/management/commands/__init__.py
notifications/management/commands/notification_sender.py
notifications/management/commands/notification_test.py
notifications/migrations/0001_initial_20210729.py
notifications/migrations/0002_auto_20210913_1046.py
notifications/migrations/0003_auto_20210913_1050.py
notifications/migrations/0004_notification_notificatio_status_d92267_idx.py
notifications/migrations/__init__.py
notifications/static/django/forms/widgets/randomgeneratetext.js
notifications/templates/admin/notifications/notification/change_form_object_tools.html
notifications/templates/admin/notifications/notification/preview_mail.html
notifications/templates/admin/notifications/notification/preview_slack.html
notifications/templates/django/forms/widgets/randomgeneratetext.html
django_notification_sender-1.0.0.dist-info/METADATA
django_notification_sender-1.0.0.dist-info/WHEEL
django_notification_sender-1.0.0.dist-info/top_level.txt
django_notification_sender-1.0.0.dist-info/RECORD
