Metadata-Version: 2.4
Name: django-notification-sender
Version: 1.0.0
Summary: Pluggable app to centralize notification configuration.
Home-page: https://github.com/surface-security/django-notification-sender
Author: PPB - InfoSec Engineering
Author-email: surface@paddypowerbetfair.com
License: MIT
Classifier: Development Status :: 5 - Production/Stable
Classifier: Framework :: Django
Classifier: License :: OSI Approved :: MIT License
Classifier: Intended Audience :: Developers
Classifier: Operating System :: OS Independent
Classifier: Programming Language :: Python
Classifier: Programming Language :: Python :: 3.9
Classifier: Environment :: Web Environment
Classifier: Topic :: Software Development
Requires-Python: >=3.9
License-File: LICENSE
Requires-Dist: Django<6.0,>=4.2
Requires-Dist: django-templated-email<4,>=2.3
Requires-Dist: html2text
Requires-Dist: slack-sdk<4,>=3.11.2
Dynamic: license-file
